azure/cognitiveservices/search/newssearch/__init__.py
azure/cognitiveservices/search/newssearch/news_search_api.py
azure/cognitiveservices/search/newssearch/version.py
azure/cognitiveservices/search/newssearch/models/__init__.py
azure/cognitiveservices/search/newssearch/models/answer.py
azure/cognitiveservices/search/newssearch/models/answer_py3.py
azure/cognitiveservices/search/newssearch/models/article.py
azure/cognitiveservices/search/newssearch/models/article_py3.py
azure/cognitiveservices/search/newssearch/models/creative_work.py
azure/cognitiveservices/search/newssearch/models/creative_work_py3.py
azure/cognitiveservices/search/newssearch/models/error.py
azure/cognitiveservices/search/newssearch/models/error_py3.py
azure/cognitiveservices/search/newssearch/models/error_response.py
azure/cognitiveservices/search/newssearch/models/error_response_py3.py
azure/cognitiveservices/search/newssearch/models/identifiable.py
azure/cognitiveservices/search/newssearch/models/identifiable_py3.py
azure/cognitiveservices/search/newssearch/models/image_object.py
azure/cognitiveservices/search/newssearch/models/image_object_py3.py
azure/cognitiveservices/search/newssearch/models/media_object.py
azure/cognitiveservices/search/newssearch/models/media_object_py3.py
azure/cognitiveservices/search/newssearch/models/news.py
azure/cognitiveservices/search/newssearch/models/news_article.py
azure/cognitiveservices/search/newssearch/models/news_article_py3.py
azure/cognitiveservices/search/newssearch/models/news_py3.py
azure/cognitiveservices/search/newssearch/models/news_search_api_enums.py
azure/cognitiveservices/search/newssearch/models/news_topic.py
azure/cognitiveservices/search/newssearch/models/news_topic_py3.py
azure/cognitiveservices/search/newssearch/models/organization.py
azure/cognitiveservices/search/newssearch/models/organization_py3.py
azure/cognitiveservices/search/newssearch/models/query.py
azure_cognitiveservices_search_newssearch-1.0.0.dist-info/METADATA
azure_cognitiveservices_search_newssearch-1.0.0.dist-info/RECORD
azure_cognitiveservices_search_newssearch-1.0.0.dist-info/WHEEL
azure_cognitiveservices_search_newssearch-1.0.0.dist-info/top_level.txt
