Metadata-Version: 2.1
Name: azure-cognitiveservices-search-newssearch
Version: 1.0.0
Summary: Microsoft Azure NewsSearch Client Library for Python
Home-page: https://github.com/Azure/azure-sdk-for-python
Author: Microsoft Corporation
Author-email: azpysdkhelp@microsoft.com
License: MIT License
Platform: UNKNOWN
Classifier: Development Status :: 5 - Production/Stable
Classifier: Programming Language :: Python
Classifier: Programming Language :: Python :: 2
Classifier: Programming Language :: Python :: 2.7
Classifier: Programming Language :: Python :: 3
Classifier: Programming Language :: Python :: 3.4
Classifier: Programming Language :: Python :: 3.5
Classifier: Programming Language :: Python :: 3.6
Classifier: License :: OSI Approved :: MIT License
Requires-Dist: msrest (<2.0.0,>=0.4.28)
Requires-Dist: azure-common (~=1.1)
Requires-Dist: azure-cognitiveservices-search-nspkg (>=2.0.0)
